iginx_pyclient/__init__.py
iginx_pyclient/cluster_info.py
iginx_pyclient/dataset.py
iginx_pyclient/session.py
iginx_pyclient/time_series.py
iginx_pyclient/thrift/__init__.py
iginx_pyclient/thrift/rpc/IService.py
iginx_pyclient/thrift/rpc/__init__.py
iginx_pyclient/thrift/rpc/constants.py
iginx_pyclient/thrift/rpc/ttypes.py
iginx_pyclient/utils/__init__.py
iginx_pyclient/utils/bitmap.py
iginx_pyclient/utils/byte_utils.py
iginx_pyclient-0.8.0.dist-info/LICENSE
iginx_pyclient-0.8.0.dist-info/METADATA
iginx_pyclient-0.8.0.dist-info/WHEEL
iginx_pyclient-0.8.0.dist-info/top_level.txt
iginx_pyclient-0.8.0.dist-info/RECORD
