Metadata-Version: 2.1
Name: iginx-pyclient
Version: 0.8.0
Summary: IGinX-PyClient
Author: THU IGinX
Author-email: TSIginX@gmail.com
License: Apache License 2.0
Requires-Python: >=3.8
License-File: LICENSE
Requires-Dist: pandas>=2.0.3
